.coveragerc
.gitignore
.travis.yml
LICENSE
MANIFEST.in
README.rst
requirements.txt
setup.cfg
setup.py
tox.ini
docs/HISTORY.rst
docs/TODO.rst
miscs/setup.sh
shiori/__init__.py
shiori/manage.py
shiori.egg-info/PKG-INFO
shiori.egg-info/SOURCES.txt
shiori.egg-info/dependency_links.txt
shiori.egg-info/requires.txt
shiori.egg-info/top_level.txt
shiori/api/__init__.py
shiori/api/permissions.py
shiori/api/serializers.py
shiori/api/urls.py
shiori/api/views.py
shiori/bookmark/__init__.py
shiori/bookmark/admin.py
shiori/bookmark/feed_generator.py
shiori/bookmark/models.py
shiori/bookmark/tasks.py
shiori/bookmark/urls.py
shiori/bookmark/validators.py
shiori/bookmark/views.py
shiori/bookmark/agents/__init__.py
shiori/bookmark/agents/feed.py
shiori/bookmark/agents/feed_parser.py
shiori/bookmark/migrations/0001_initial.py
shiori/bookmark/migrations/0002_auto__del_unique_bookmark_url__add_unique_bookmark_url_owner.py
shiori/bookmark/migrations/0003_auto__add_crawlinghistory__add_feedsubscription__add_unique_feedsubscr.py
shiori/bookmark/migrations/0004_auto__add_field_crawlinghistory_result__chg_field_crawlinghistory_upda.py
shiori/bookmark/migrations/__init__.py
shiori/core/__init__.py
shiori/core/celery.py
shiori/core/settings.py
shiori/core/urls.py
shiori/core/wsgi.py
shiori/static/css/main.css
shiori/static/js/html-sanitizer.js
shiori/static/js/html4-defs.js
shiori/static/js/main.js
shiori/templates/layout.html
shiori/templates/bookmark/bookmark.html
shiori/templates/bookmark/categories.html
shiori/templates/bookmark/category.html
shiori/templates/bookmark/edit.html
shiori/templates/bookmark/feed_subscription.html
shiori/templates/bookmark/index.html
shiori/templates/bookmark/logout.html
shiori/templates/bookmark/profile.html
shiori/templates/bookmark/tag.html
shiori/templates/bookmark/tags.html
shiori/templates/feeds/latest_title.html
shiori_tests/__init__.py
shiori_tests/manage.py
shiori_tests/run_tests.py
shiori_tests/settings.py
shiori_tests/test_data/FakeNameGenerator.com_2a6e893c.csv
shiori_tests/test_data/csv2json.py
shiori_tests/test_data/dummy_rss.xml
shiori_tests/test_data/generate_data.py
