Metadata-Version: 1.1
Name: shiori
Version: 0.4.0
Summary: bookmarking tool based on Web UI and JSON REST API
Home-page: https://github.com/mkouhei/shiori
Author: Kouhei Maeda
Author-email: mkouhei@palmtb.net
License: GNU General Public License version 3
Platform: UNKNOWN
Classifier: Development Status :: 3 - Alpha
Classifier: License :: OSI Approved :: GNU General Public License v3 or later (GPLv3+)
Classifier: Programming Language :: Python
Classifier: Programming Language :: Python :: 2.7
Classifier: Programming Language :: Python :: Implementation :: CPython
Classifier: Topic :: Internet
Classifier: Topic :: Internet :: WWW/HTTP
Classifier: Topic :: Internet :: WWW/HTTP :: WSGI :: Application
